vloc/__init__.py
vloc/plugin/__info__.py
vloc/plugin/__init__.py
vloc/plugin/__plugin__.py
vloc_plugin-0.0.7.dist-info/LICENSE.txt
vloc_plugin-0.0.7.dist-info/METADATA
vloc_plugin-0.0.7.dist-info/WHEEL
vloc_plugin-0.0.7.dist-info/top_level.txt
vloc_plugin-0.0.7.dist-info/RECORD
